Xsequential/Modelmetada.py
Xsequential/__init__.py
Xsequential/app.py
Xsequential/custompr.py
Xsequential/custompredict.py
Xsequential/fashioncnn.py
Xsequential/jav.py
Xsequential/temp.py
Xsequential/xSequential.py
Xsequential/static/css/sb-admin.css
Xsequential/static/css/sb-admin.min.css
Xsequential/static/js/Chart.bundle.js
Xsequential/static/js/bootstrap-table-filter.js
Xsequential/static/js/bs-table.js
Xsequential/static/js/bsf.js
Xsequential/static/js/bst.js
Xsequential/static/js/ex_bootstrap-table-filter.js
Xsequential/static/js/moment.js
Xsequential/static/js/sb-admin.js
Xsequential/static/js/sb-admin.min.js
Xsequential/static/js/utlis.js
Xsequential/static/js/demo/chart-area-demo.js
Xsequential/static/js/demo/chart-bar-demo.js
Xsequential/static/js/demo/chart-pie-demo.js
Xsequential/static/js/demo/datatables-demo.js
Xsequential/static/scss/_cards.scss
Xsequential/static/scss/_footer.scss
Xsequential/static/scss/_global.scss
Xsequential/static/scss/_login.scss
Xsequential/static/scss/_mixins.scss
Xsequential/static/scss/_navbar.scss
Xsequential/static/scss/_utilities.scss
Xsequential/static/scss/_variables.scss
Xsequential/static/scss/sb-admin.scss
Xsequential/static/vendor/bootstrap/css/bootstrap-grid.css
Xsequential/static/vendor/bootstrap/css/bootstrap-grid.min.css
Xsequential/static/vendor/bootstrap/css/bootstrap-reboot.css
Xsequential/static/vendor/bootstrap/css/bootstrap-reboot.min.css
Xsequential/static/vendor/bootstrap/css/bootstrap.css
Xsequential/static/vendor/bootstrap/css/bootstrap.css.map
Xsequential/static/vendor/bootstrap/css/bootstrap.min.css
Xsequential/static/vendor/bootstrap/css/bootstrap.min.css.map
Xsequential/static/vendor/bootstrap/js/bootstrap.bundle.js
Xsequential/static/vendor/bootstrap/js/bootstrap.bundle.js.map
Xsequential/static/vendor/bootstrap/js/bootstrap.bundle.min.js
Xsequential/static/vendor/bootstrap/js/bootstrap.bundle.min.js.map
Xsequential/static/vendor/bootstrap/js/bootstrap.js
testmodelkb1-4.0.0.dist-info/LICENSE
testmodelkb1-4.0.0.dist-info/METADATA
testmodelkb1-4.0.0.dist-info/WHEEL
testmodelkb1-4.0.0.dist-info/top_level.txt
testmodelkb1-4.0.0.dist-info/RECORD
