Metadata-Version: 2.1
Name: testmodelkb1
Version: 4.0.0
Summary: ModelKB
Home-page: https://github.com/SirishaRella/Xsequential_package
Author: Sirisha Rella
Author-email: srnk2@mail.umkc.edu
License: UNKNOWN
Platform: UNKNOWN
Classifier: Programming Language :: Python :: 3
Requires-Dist: Flask
